cacheia_client/__init__.py
cacheia_client/client.py
cacheia_client/exceptions.py
cacheia_client-1.0.0.post3.dist-info/METADATA
cacheia_client-1.0.0.post3.dist-info/WHEEL
cacheia_client-1.0.0.post3.dist-info/top_level.txt
cacheia_client-1.0.0.post3.dist-info/RECORD
