Metadata-Version: 2.1
Name: cacheia_client
Version: 1.0.0.post3
Summary: Client for cacheia service that allows invalidation and other shenanigans
Author-email: TeiaLabs <contato@teialabs.com>
Keywords: client,cache,http,service
Requires-Python: >=3.12
Requires-Dist: httpx ~=0.27
Provides-Extra: dev
Requires-Dist: black <25,>=24 ; extra == 'dev'
Requires-Dist: isort <6,>=5 ; extra == 'dev'
Requires-Dist: pytest <9,>=8 ; extra == 'dev'
Provides-Extra: schemas
Requires-Dist: cacheia-schemas ==1.0.0 ; extra == 'schemas'
